crea_graphenelib-0.1.3.dist-info/METADATA
crea_graphenelib-0.1.3.dist-info/RECORD
crea_graphenelib-0.1.3.dist-info/WHEEL
crea_graphenelib-0.1.3.dist-info/top_level.txt
grapheneapi/__init__.py
grapheneapi/api.py
grapheneapi/exceptions.py
grapheneapi/grapheneapi.py
grapheneapi/grapheneclient.py
grapheneapi/graphenehttprpc.py
grapheneapi/graphenews.py
grapheneapi/graphenewsprotocol.py
grapheneapi/graphenewsrpc.py
grapheneapi/http.py
grapheneapi/rpc.py
grapheneapi/websocket.py
graphenebase/__init__.py
graphenebase/account.py
graphenebase/base58.py
graphenebase/bip38.py
graphenebase/chains.py
graphenebase/dictionary.py
graphenebase/ecdsa.py
graphenebase/objects.py
graphenebase/objecttypes.py
graphenebase/operationids.py
graphenebase/operations.py
graphenebase/signedtransactions.py
graphenebase/transactions.py
graphenebase/types.py
