Metadata-Version: 2.1
Name: crea-graphenelib
Version: 0.1.3
Summary: Python library for graphene-based blockchains
Home-page: http://www.github.com/creativechain/crea-python-graphenelib
Author: Creativechain Foundation
Author-email: info@creativechain.org
Maintainer: Creativechain Foundation
Maintainer-email: info@creativechain.org
License: UNKNOWN
Download-URL: https://github.com/creativechain/crea-python-graphenelib/tarball/0.1.3
Keywords: graphene,api,rpc,ecdsa,secp256k1
Platform: UNKNOWN
Classifier: License :: OSI Approved :: MIT License
Classifier: Operating System :: OS Independent
Classifier: Programming Language :: Python :: 3
Classifier: Development Status :: 3 - Alpha
Classifier: Intended Audience :: Developers
Requires-Dist: ecdsa
Requires-Dist: requests
Requires-Dist: websocket-client
Requires-Dist: pylibscrypt
Requires-Dist: pycryptodome
